odoo/addons/pos_report_order_payment/README.rst
odoo/addons/pos_report_order_payment/__init__.py
odoo/addons/pos_report_order_payment/__manifest__.py
odoo/addons/pos_report_order_payment/i18n/es.po
odoo/addons/pos_report_order_payment/i18n/fr.po
odoo/addons/pos_report_order_payment/i18n/pos_report_order_payment.pot
odoo/addons/pos_report_order_payment/readme/CONTRIBUTORS.rst
odoo/addons/pos_report_order_payment/readme/DESCRIPTION.rst
odoo/addons/pos_report_order_payment/readme/USAGE.rst
odoo/addons/pos_report_order_payment/report/__init__.py
odoo/addons/pos_report_order_payment/report/pos_order_payment_report.py
odoo/addons/pos_report_order_payment/report/pos_order_payment_report.xml
odoo/addons/pos_report_order_payment/security/ir.model.access.csv
odoo/addons/pos_report_order_payment/static/description/graph.png
odoo/addons/pos_report_order_payment/static/description/icon.png
odoo/addons/pos_report_order_payment/static/description/index.html
odoo/addons/pos_report_order_payment/static/description/pivot.png
odoo12_addon_pos_report_order_payment-12.0.1.0.1.dist-info/METADATA
odoo12_addon_pos_report_order_payment-12.0.1.0.1.dist-info/WHEEL
odoo12_addon_pos_report_order_payment-12.0.1.0.1.dist-info/top_level.txt
odoo12_addon_pos_report_order_payment-12.0.1.0.1.dist-info/RECORD
