Metadata-Version: 2.1
Name: odoo12-addon-pos-report-order-payment
Version: 12.0.1.0.1
Summary: Analyze point of sale payments
Home-page: https://github.com/OCA/pos
Author: Druidoo, Moka Tourisme, Odoo Community Association (OCA)
Author-email: support@odoo-community.org
License: AGPL-3
Platform: UNKNOWN
Classifier: Programming Language :: Python
Classifier: Framework :: Odoo
Classifier: License :: OSI Approved :: GNU Affero General Public License v3
Requires-Python: >=3.5
Requires-Dist: odoo (<12.1dev,>=12.0a)
